kv/azure/blob/__init__.py
kv/azure/blob/__init__.pyi
kv/azure/blob/blob.py
kv/azure/blob/container.py
kv/azure/blob/util.py
kv_azure_blob-0.1.9.dist-info/METADATA
kv_azure_blob-0.1.9.dist-info/WHEEL
kv_azure_blob-0.1.9.dist-info/top_level.txt
kv_azure_blob-0.1.9.dist-info/RECORD
