Metadata-Version: 2.1
Name: kv-azure-blob
Version: 0.1.9
Summary: KV API implementation on Azure Blob Storage
Author-email: Marcel Claramunt <marcel@moveread.com>
Project-URL: repo, https://github.com/marciclabas/python-storage.git
Requires-Python: >=3.10
Requires-Dist: azure-storage-blob
Requires-Dist: aiohttp
Requires-Dist: haskellian
Requires-Dist: lazy-loader
